mailtm/__init__.py
mailtm/email.py
mailtm/message.py
MailTm-0.0.81.dist-info/LICENSE
MailTm-0.0.81.dist-info/METADATA
MailTm-0.0.81.dist-info/WHEEL
MailTm-0.0.81.dist-info/top_level.txt
MailTm-0.0.81.dist-info/RECORD
