Metadata-Version: 2.1
Name: MailTm
Version: 0.0.81
Summary: Temporary Email
Home-page: https://github.com/MainSilent/MailTm
Author: MainSilent
License: UNKNOWN
Project-URL: Bug Tracker, https://github.com/MainSilent/MailTm/issues
Keywords: mail,email,temporary mail,temporary email,mailtm
Platform: UNKNOWN
Classifier: Programming Language :: Python :: 3
Classifier: License :: OSI Approved :: MIT License
Classifier: Operating System :: OS Independent
Requires-Python: >=3.6
License-File: LICENSE
Requires-Dist: requests
